PYSTOIC/__init__.py
PYSTOIC/codemod.py
PYSTOIC/config.py
PYSTOIC/models.py
PYSTOIC/reader.py
PYSTOIC/runner.py
PYSTOIC/setup.py
PYSTOIC/utils.py
PYSTOIC/requirements/__init__.py
PYSTOIC/requirements/commits.py
PYSTOIC/requirements/display.py
PYSTOIC/requirements/install.py
PYSTOIC/requirements/install_api.py
PYSTOIC/requirements/resolve.py
PYSTOIC/requirements/utils.py
PYSTOIC-0.2.4.dist-info/METADATA
PYSTOIC-0.2.4.dist-info/WHEEL
PYSTOIC-0.2.4.dist-info/top_level.txt
PYSTOIC-0.2.4.dist-info/RECORD
